aimat/__init__.py
aimat/__main__.py
aimat/cli.py
aimat/osc_listener.py
aimat/docker/.env
aimat/docker/__init__.py
aimat/docker/docker-compose.yml
aimat-0.1.6.dist-info/licenses/LICENSE
aimat-0.1.6.dist-info/METADATA
aimat-0.1.6.dist-info/WHEEL
aimat-0.1.6.dist-info/entry_points.txt
aimat-0.1.6.dist-info/top_level.txt
aimat-0.1.6.dist-info/RECORD
