Metadata-Version: 2.4
Name: aimat
Version: 0.1.6
Summary: AIMAT: AI Music Artist Toolkit - Simplified AI Music workflows.
Author: Eric Browne
License: MIT
License-File: LICENSE
Requires-Dist: python-osc
Requires-Dist: docker
Requires-Dist: psutil
Dynamic: license-file
